bananaproai_com/__init__.py
bananaproai_com-1767063.908.307.dist-info/licenses/LICENSE
bananaproai_com-1767063.908.307.dist-info/METADATA
bananaproai_com-1767063.908.307.dist-info/WHEEL
bananaproai_com-1767063.908.307.dist-info/top_level.txt
bananaproai_com-1767063.908.307.dist-info/RECORD
