Metadata-Version: 2.4
Name: bananaproai-com
Version: 1767063.908.307
Summary: High-quality integration for https://bananaproai.com/
Home-page: https://bananaproai.com/
Author: SuperMaker
Classifier: Programming Language :: Python :: 3
Classifier: License :: OSI Approved :: MIT License
Requires-Python: >=3.6
License-File: LICENSE
Dynamic: author
Dynamic: classifier
Dynamic: description
Dynamic: description-content-type
Dynamic: home-page
Dynamic: license-file
Dynamic: requires-python
Dynamic: summary
